typewebio/__init__.py
typewebio/baseui.py
typewebio/bootstrap.py
typewebio/core.py
typewebio/input.py
typewebio/output.py
typewebio/pin.py
typewebio/session.py
typewebio-0.0.2.dist-info/LICENSE
typewebio-0.0.2.dist-info/METADATA
typewebio-0.0.2.dist-info/WHEEL
typewebio-0.0.2.dist-info/top_level.txt
typewebio-0.0.2.dist-info/RECORD
